[{"from":{"province_name":"","province_pinyin":"","city_name":"天津市","city_pinyin":"","station_name":"大港油田","location":""},"to":{"province_name":"","province_pinyin":"","city_name":"大城","city_pinyin":"","station_name":"大城","location":""},"info":{"distance":"147km","departure_time":["00:00"],"price":"￥40.00","models":"中型","telephone":"","Pass_by":"大港油田 → 大城 → 任丘"}},{"from":{"province_name":"","province_pinyin":"","city_name":"天津市","city_pinyin":"","station_name":"","location":""},"to":{"province_name":"","province_pinyin":"","city_name":"大城","city_pinyin":"","station_name":"大城","location":""},"info":{"distance":"147km","departure_time":["07:15"],"price":"￥40.00","models":"中型","telephone":"","Pass_by":""}},{"from":{"province_name":"","province_pinyin":"","city_name":"天津市","city_pinyin":"","station_name":"","location":""},"to":{"province_name":"","province_pinyin":"","city_name":"大城","city_pinyin":"","station_name":"大城","location":""},"info":{"distance":"147km","departure_time":["08:20"],"price":"￥40.00","models":"中型","telephone":"","Pass_by":""}},{"from":{"province_name":"","province_pinyin":"","city_name":"天津市","city_pinyin":"","station_name":"","location":""},"to":{"province_name":"","province_pinyin":"","city_name":"大城","city_pinyin":"","station_name":"大城","location":""},"info":{"distance":"147km","departure_time":["08:20"],"price":"￥40.00","models":"中型","telephone":"","Pass_by":""}},{"from":{"province_name":"","province_pinyin":"","city_name":"天津市","city_pinyin":"","station_name":"","location":""},"to":{"province_name":"","province_pinyin":"","city_name":"大城","city_pinyin":"","station_name":"大城","location":""},"info":{"distance":"147km","departure_time":["08:20"],"price":"￥40.00","models":"中型","telephone":"","Pass_by":""}},{"from":{"province_name":"","province_pinyin":"","city_name":"天津市","city_pinyin":"","station_name":"","location":""},"to":{"province_name":"","province_pinyin":"","city_name":"大城","city_pinyin":"","station_name":"大城","location":""},"info":{"distance":"147km","departure_time":["13:20"],"price":"￥40.00","models":"中型","telephone":"","Pass_by":""}},{"from":{"province_name":"","province_pinyin":"","city_name":"天津市","city_pinyin":"","station_name":"","location":""},"to":{"province_name":"","province_pinyin":"","city_name":"大城","city_pinyin":"","station_name":"大城","location":""},"info":{"distance":"147km","departure_time":["14:30"],"price":"￥40.00","models":"中型","telephone":"","Pass_by":""}},{"from":{"province_name":"","province_pinyin":"","city_name":"天津市","city_pinyin":"","station_name":"大港油田","location":""},"to":{"province_name":"","province_pinyin":"","city_name":"博野","city_pinyin":"","station_name":"博野","location":""},"info":{"distance":"266km","departure_time":["08:20"],"price":"￥72.00","models":"中型","telephone":"","Pass_by":"大港油田 → 博野 → 定州"}},{"from":{"province_name":"","province_pinyin":"","city_name":"天津市","city_pinyin":"","station_name":"","location":""},"to":{"province_name":"","province_pinyin":"","city_name":"博野","city_pinyin":"","station_name":"博野","location":""},"info":{"distance":"266km","departure_time":["08:20"],"price":"￥72.00","models":"中型","telephone":"","Pass_by":""}},{"from":{"province_name":"","province_pinyin":"","city_name":"天津市","city_pinyin":"","station_name":"","location":""},"to":{"province_name":"","province_pinyin":"","city_name":"博野","city_pinyin":"","station_name":"博野","location":""},"info":{"distance":"266km","departure_time":["08:20"],"price":"￥72.00","models":"中型","telephone":"","Pass_by":""}},{"from":{"province_name":"","province_pinyin":"","city_name":"天津市","city_pinyin":"","station_name":"大港油田","location":""},"to":{"province_name":"","province_pinyin":"","city_name":"安国","city_pinyin":"","station_name":"安国","location":""},"info":{"distance":"266km","departure_time":["08:20"],"price":"￥72.00","models":"中型","telephone":"","Pass_by":"大港油田 → 安国 → 定州"}},{"from":{"province_name":"","province_pinyin":"","city_name":"天津市","city_pinyin":"","station_name":"","location":""},"to":{"province_name":"","province_pinyin":"","city_name":"安国","city_pinyin":"","station_name":"安国","location":""},"info":{"distance":"266km","departure_time":["08:20"],"price":"￥72.00","models":"中型","telephone":"","Pass_by":""}},{"from":{"province_name":"","province_pinyin":"","city_name":"天津市","city_pinyin":"","station_name":"","location":""},"to":{"province_name":"","province_pinyin":"","city_name":"安国","city_pinyin":"","station_name":"安国","location":""},"info":{"distance":"266km","departure_time":["08:20"],"price":"￥72.00","models":"中型","telephone":"","Pass_by":""}},{"from":{"province_name":"","province_pinyin":"","city_name":"天津市","city_pinyin":"","station_name":"大港油田","location":""},"to":{"province_name":"","province_pinyin":"","city_name":"高阳","city_pinyin":"","station_name":"高阳","location":""},"info":{"distance":"221km","departure_time":["07:40"],"price":"￥60.00","models":"中型","telephone":"","Pass_by":"大港油田 → 高阳 → 保定"}},{"from":{"province_name":"","province_pinyin":"","city_name":"天津市","city_pinyin":"","station_name":"","location":""},"to":{"province_name":"","province_pinyin":"","city_name":"高阳","city_pinyin":"","station_name":"高阳","location":""},"info":{"distance":"221km","departure_time":["07:40"],"price":"￥60.00","models":"中型","telephone":"","Pass_by":""}},{"from":{"province_name":"","province_pinyin":"","city_name":"天津市","city_pinyin":"","station_name":"","location":""},"to":{"province_name":"","province_pinyin":"","city_name":"高阳","city_pinyin":"","station_name":"高阳","location":""},"info":{"distance":"221km","departure_time":["07:40"],"price":"￥60.00","models":"中型","telephone":"","Pass_by":""}},{"from":{"province_name":"","province_pinyin":"","city_name":"天津市","city_pinyin":"","station_name":"大港油田","location":""},"to":{"province_name":"","province_pinyin":"","city_name":"蠡县","city_pinyin":"","station_name":"蠡县","location":""},"info":{"distance":"258km","departure_time":["08:20"],"price":"￥70.00","models":"中型","telephone":"","Pass_by":"大港油田 → 蠡县 → 定州"}},{"from":{"province_name":"","province_pinyin":"","city_name":"天津市","city_pinyin":"","station_name":"","location":""},"to":{"province_name":"","province_pinyin":"","city_name":"蠡县","city_pinyin":"","station_name":"蠡县","location":""},"info":{"distance":"258km","departure_time":["08:20"],"price":"￥70.00","models":"中型","telephone":"","Pass_by":""}},{"from":{"province_name":"","province_pinyin":"","city_name":"天津市","city_pinyin":"","station_name":"","location":""},"to":{"province_name":"","province_pinyin":"","city_name":"蠡县","city_pinyin":"","station_name":"蠡县","location":""},"info":{"distance":"258km","departure_time":["08:20"],"price":"￥70.00","models":"中型","telephone":"","Pass_by":""}},{"from":{"province_name":"","province_pinyin":"","city_name":"天津市","city_pinyin":"","station_name":"大港油田","location":""},"to":{"province_name":"","province_pinyin":"","city_name":"乐陵","city_pinyin":"","station_name":"乐陵","location":""},"info":{"distance":"247km","departure_time":["07:20"],"price":"￥67.00","models":"中型","telephone":"","Pass_by":"大港油田 → 乐陵 → 济南"}},{"from":{"province_name":"","province_pinyin":"","city_name":"天津市","city_pinyin":"","station_name":"","location":""},"to":{"province_name":"","province_pinyin":"","city_name":"乐陵","city_pinyin":"","station_name":"乐陵","location":""},"info":{"distance":"166km","departure_time":["16:00"],"price":"￥86.00","models":"--","telephone":"","Pass_by":""}},{"from":{"province_name":"","province_pinyin":"","city_name":"天津市","city_pinyin":"","station_name":"大港油田","location":""},"to":{"province_name":"","province_pinyin":"","city_name":"任丘","city_pinyin":"","station_name":"任丘","location":""},"info":{"distance":"184km","departure_time":["00:00"],"price":"￥50.00","models":"中型","telephone":"","Pass_by":"大港油田 → 任丘"}},{"from":{"province_name":"","province_pinyin":"","city_name":"天津市","city_pinyin":"","station_name":"","location":""},"to":{"province_name":"","province_pinyin":"","city_name":"任丘","city_pinyin":"","station_name":"任丘","location":""},"info":{"distance":"184km","departure_time":["07:15"],"price":"￥50.00","models":"中型","telephone":"","Pass_by":""}},{"from":{"province_name":"","province_pinyin":"","city_name":"天津市","city_pinyin":"","station_name":"","location":""},"to":{"province_name":"","province_pinyin":"","city_name":"任丘","city_pinyin":"","station_name":"任丘","location":""},"info":{"distance":"184km","departure_time":["08:20"],"price":"￥50.00","models":"中型","telephone":"","Pass_by":""}},{"from":{"province_name":"","province_pinyin":"","city_name":"天津市","city_pinyin":"","station_name":"","location":""},"to":{"province_name":"","province_pinyin":"","city_name":"任丘","city_pinyin":"","station_name":"任丘","location":""},"info":{"distance":"184km","departure_time":["08:20"],"price":"￥50.00","models":"中型","telephone":"","Pass_by":""}},{"from":{"province_name":"","province_pinyin":"","city_name":"天津市","city_pinyin":"","station_name":"","location":""},"to":{"province_name":"","province_pinyin":"","city_name":"任丘","city_pinyin":"","station_name":"任丘","location":""},"info":{"distance":"184km","departure_time":["08:20"],"price":"￥50.00","models":"中型","telephone":"","Pass_by":""}},{"from":{"province_name":"","province_pinyin":"","city_name":"天津市","city_pinyin":"","station_name":"","location":""},"to":{"province_name":"","province_pinyin":"","city_name":"任丘","city_pinyin":"","station_name":"任丘","location":""},"info":{"distance":"184km","departure_time":["13:20"],"price":"￥50.00","models":"中型","telephone":"","Pass_by":""}},{"from":{"province_name":"","province_pinyin":"","city_name":"天津市","city_pinyin":"","station_name":"","location":""},"to":{"province_name":"","province_pinyin":"","city_name":"任丘","city_pinyin":"","station_name":"任丘","location":""},"info":{"distance":"184km","departure_time":["14:30"],"price":"￥50.00","models":"中型","telephone":"","Pass_by":""}},{"from":{"province_name":"","province_pinyin":"","city_name":"天津市","city_pinyin":"","station_name":"","location":""},"to":{"province_name":"","province_pinyin":"","city_name":"任丘","city_pinyin":"","station_name":"任丘","location":""},"info":{"distance":"324km","departure_time":["08:15"],"price":"￥37.00","models":"--","telephone":"","Pass_by":""}},{"from":{"province_name":"","province_pinyin":"","city_name":"天津市","city_pinyin":"","station_name":"大港油田","location":""},"to":{"province_name":"","province_pinyin":"","city_name":"板东","city_pinyin":"","station_name":"板东","location":""},"info":{"distance":"166km","departure_time":["13:00"],"price":"￥45.00","models":"中型","telephone":"","Pass_by":"大港油田 → 板东 → 徐水"}},{"from":{"province_name":"","province_pinyin":"","city_name":"天津市","city_pinyin":"","station_name":"大港油田","location":""},"to":{"province_name":"","province_pinyin":"","city_name":"旧城","city_pinyin":"","station_name":"旧城","location":""},"info":{"distance":"199km","departure_time":["07:40"],"price":"￥54.00","models":"中型","telephone":"","Pass_by":"大港油田 → 旧城 → 保定"}},{"from":{"province_name":"","province_pinyin":"","city_name":"天津市","city_pinyin":"","station_name":"","location":""},"to":{"province_name":"","province_pinyin":"","city_name":"旧城","city_pinyin":"","station_name":"旧城","location":""},"info":{"distance":"199km","departure_time":["07:40"],"price":"￥54.00","models":"中型","telephone":"","Pass_by":""}},{"from":{"province_name":"","province_pinyin":"","city_name":"天津市","city_pinyin":"","station_name":"","location":""},"to":{"province_name":"","province_pinyin":"","city_name":"旧城","city_pinyin":"","station_name":"旧城","location":""},"info":{"distance":"199km","departure_time":["07:40"],"price":"￥54.00","models":"中型","telephone":"","Pass_by":""}},{"from":{"province_name":"","province_pinyin":"","city_name":"天津市","city_pinyin":"","station_name":"大港油田","location":""},"to":{"province_name":"","province_pinyin":"","city_name":"徐水","city_pinyin":"","station_name":"徐水","location":""},"info":{"distance":"210km","departure_time":["13:00"],"price":"￥57.00","models":"中型","telephone":"","Pass_by":"大港油田 → 徐水"}},{"from":{"province_name":"","province_pinyin":"","city_name":"天津市","city_pinyin":"","station_name":"大港油田","location":""},"to":{"province_name":"","province_pinyin":"","city_name":"定州","city_pinyin":"","station_name":"定州","location":""},"info":{"distance":"307km","departure_time":["08:20"],"price":"￥83.00","models":"中型","telephone":"","Pass_by":"大港油田 → 定州"}},{"from":{"province_name":"","province_pinyin":"","city_name":"天津市","city_pinyin":"","station_name":"","location":""},"to":{"province_name":"","province_pinyin":"","city_name":"定州","city_pinyin":"","station_name":"定州","location":""},"info":{"distance":"307km","departure_time":["08:20"],"price":"￥83.00","models":"中型","telephone":"","Pass_by":""}},{"from":{"province_name":"","province_pinyin":"","city_name":"天津市","city_pinyin":"","station_name":"","location":""},"to":{"province_name":"","province_pinyin":"","city_name":"定州","city_pinyin":"","station_name":"定州","location":""},"info":{"distance":"307km","departure_time":["08:20"],"price":"￥83.00","models":"中型","telephone":"","Pass_by":""}},{"from":{"province_name":"","province_pinyin":"","city_name":"天津市","city_pinyin":"","station_name":"","location":""},"to":{"province_name":"","province_pinyin":"","city_name":"定州","city_pinyin":"","station_name":"定州","location":""},"info":{"distance":"371km","departure_time":["07:00"],"price":"￥83.00","models":"--","telephone":"","Pass_by":""}},{"from":{"province_name":"","province_pinyin":"","city_name":"天津市","city_pinyin":"","station_name":"","location":""},"to":{"province_name":"","province_pinyin":"","city_name":"定州","city_pinyin":"","station_name":"定州","location":""},"info":{"distance":"371km","departure_time":["09:30"],"price":"￥83.00","models":"--","telephone":"","Pass_by":""}},{"from":{"province_name":"","province_pinyin":"","city_name":"天津市","city_pinyin":"","station_name":"","location":""},"to":{"province_name":"","province_pinyin":"","city_name":"定州","city_pinyin":"","station_name":"定州","location":""},"info":{"distance":"371km","departure_time":["13:40"],"price":"￥83.00","models":"--","telephone":"","Pass_by":""}},{"from":{"province_name":"","province_pinyin":"","city_name":"天津市","city_pinyin":"","station_name":"大港油田","location":""},"to":{"province_name":"","province_pinyin":"","city_name":"流河","city_pinyin":"","station_name":"流河","location":""},"info":{"distance":"129km","departure_time":["00:00"],"price":"￥35.00","models":"中型","telephone":"","Pass_by":"大港油田 → 流河 → 任丘"}},{"from":{"province_name":"","province_pinyin":"","city_name":"天津市","city_pinyin":"","station_name":"","location":""},"to":{"province_name":"","province_pinyin":"","city_name":"流河","city_pinyin":"","station_name":"流河","location":""},"info":{"distance":"129km","departure_time":["07:15"],"price":"￥35.00","models":"中型","telephone":"","Pass_by":""}},{"from":{"province_name":"","province_pinyin":"","city_name":"天津市","city_pinyin":"","station_name":"","location":""},"to":{"province_name":"","province_pinyin":"","city_name":"流河","city_pinyin":"","station_name":"流河","location":""},"info":{"distance":"129km","departure_time":["08:20"],"price":"￥35.00","models":"中型","telephone":"","Pass_by":""}},{"from":{"province_name":"","province_pinyin":"","city_name":"天津市","city_pinyin":"","station_name":"","location":""},"to":{"province_name":"","province_pinyin":"","city_name":"流河","city_pinyin":"","station_name":"流河","location":""},"info":{"distance":"129km","departure_time":["08:20"],"price":"￥35.00","models":"中型","telephone":"","Pass_by":""}},{"from":{"province_name":"","province_pinyin":"","city_name":"天津市","city_pinyin":"","station_name":"","location":""},"to":{"province_name":"","province_pinyin":"","city_name":"流河","city_pinyin":"","station_name":"流河","location":""},"info":{"distance":"129km","departure_time":["08:20"],"price":"￥35.00","models":"中型","telephone":"","Pass_by":""}},{"from":{"province_name":"","province_pinyin":"","city_name":"天津市","city_pinyin":"","station_name":"","location":""},"to":{"province_name":"","province_pinyin":"","city_name":"流河","city_pinyin":"","station_name":"流河","location":""},"info":{"distance":"129km","departure_time":["13:20"],"price":"￥35.00","models":"中型","telephone":"","Pass_by":""}},{"from":{"province_name":"","province_pinyin":"","city_name":"天津市","city_pinyin":"","station_name":"","location":""},"to":{"province_name":"","province_pinyin":"","city_name":"流河","city_pinyin":"","station_name":"流河","location":""},"info":{"distance":"129km","departure_time":["14:30"],"price":"￥35.00","models":"中型","telephone":"","Pass_by":""}}]