[{"city_name":"重庆市","station_name":"重庆市璧山县青杠汽车站","telephone":"023-41780426","address":"重庆市璧山县城青杠街道"},{"city_name":"重庆市","station_name":"重庆市南坪汽车站","telephone":"023-62909206","address":"重庆市南岸区南坪南路15号(万达广场对面）"},{"city_name":"重庆市","station_name":"重庆市大足县汽车站","telephone":"023-43722051","address":"重庆市大足区庄塔路"},{"city_name":"重庆市","station_name":"重庆市大足县万古汽车站","telephone":"023-43450552","address":"重庆市万古镇米市街"},{"city_name":"重庆市","station_name":"重庆市大足县龙水汽车站","telephone":"023-43624468","address":"重庆市县大足县龙水幸光路"},{"city_name":"重庆市","station_name":"重庆市大足县汽车客运中心","telephone":"023-43737620","address":"重庆市大足县龙中路15号"},{"city_name":"重庆市","station_name":"重庆市垫江汽车客运站","telephone":"023-74603267","address":"重庆市垫江县桂溪镇牡丹大道南侧迎春河处"},{"city_name":"重庆市","station_name":"重庆市垫江汽车南站","telephone":"暂无信息","address":"重庆市垫江县桂南大道"},{"city_name":"重庆市","station_name":"重庆市丰都汽车客运站","telephone":"023-70738101","address":"重庆市丰都滨江西路附近"},{"city_name":"重庆市","station_name":"重庆市奉节国平汽车客运站","telephone":"023-85985027","address":"重庆市奉节县诗城路"},{"city_name":"重庆市","station_name":"重庆市奉节长途汽车站","telephone":"023-56558337","address":"重庆市奉节县诗城路"},{"city_name":"重庆市","station_name":"重庆市奉节汽车客运总站","telephone":"023-56521051","address":"重庆市奉节县永安镇诗城路"},{"city_name":"重庆市","station_name":"重庆市梁平云龙客运站","telephone":"暂无信息","address":"重庆市龙溪路103号附近"},{"city_name":"重庆市","station_name":"重庆市中心汽车站","telephone":"暂无信息","address":"重庆市梁平县"},{"city_name":"重庆市","station_name":"重庆市涪陵区李渡汽车客运站","telephone":"暂无信息","address":"重庆市涪陵区李渡镇新民路28号"},{"city_name":"重庆市","station_name":"重庆市涪陵区新妙汽车客运站","telephone":"暂无信息","address":"重庆市涪陵区"},{"city_name":"重庆市","station_name":"重庆市涪陵区秋月门汽车站","telephone":"023-72882272","address":"重庆市涪陵区中山西路(秋月门附近)"},{"city_name":"重庆市","station_name":"重庆市涪陵区客运西站","telephone":"023-72801188","address":"重庆市涪陵区白花路(涪陵西大门鹅颈关路立交桥旁)"},{"city_name":"重庆市","station_name":"重庆市涪陵区汽车客运中心","telephone":"023-72224111","address":"重庆市涪陵区涪陵兴华东路10号"},{"city_name":"重庆市","station_name":"重庆市璧山县北门汽车站","telephone":"023-41421228","address":"重庆市璧城街道璧兴路10号"},{"city_name":"重庆市","station_name":"重庆市璧山县汽车总站","telephone":"023-41401634","address":"重庆市璧山县璧城镇璧渝路"},{"city_name":"重庆市","station_name":"重庆市开县中心客运站","telephone":"023-52262173","address":"重庆市开县新城汽车中心客运中心站平桥7号地"},{"city_name":"重庆市","station_name":"重庆市开县陈家汽车客运站","telephone":"023-52532040","address":"重庆市开县长沙镇田橙路190号"},{"city_name":"重庆市","station_name":"重庆市开县太原客运站","telephone":"023-52862399","address":"重庆市开县临江新龙街100号向东"},{"city_name":"重庆市","station_name":"重庆市北碚汽车站","telephone":"023-68862380","address":"重庆市北碚区云华路155号"},{"city_name":"重庆市","station_name":"重庆市北碚区柳荫汽车站","telephone":"暂无信息","address":"重庆市北碚区碚峡路144号"},{"city_name":"重庆市","station_name":"重庆市汽车运输公司北碚总站","telephone":"023-68861550","address":"重庆市北碚区碚峡路262号"},{"city_name":"重庆市","station_name":"重庆市长寿凤城车站","telephone":"023-40232806","address":"重庆市长寿路"},{"city_name":"重庆市","station_name":"重庆市川维汽车站","telephone":"023-40704483","address":"重庆市长寿区川维镇"},{"city_name":"重庆市","station_name":"重庆市长寿汽车西站","telephone":"023-40712666","address":"重庆市长寿区双园支路3号"},{"city_name":"重庆市","station_name":"重庆市长寿汽车客运总站","telephone":"023-40463346","address":"重庆市长寿区"},{"city_name":"重庆市","station_name":"重庆市江津区白沙汽车站","telephone":"023-47335626","address":"重庆市江津区白沙镇外宾路"},{"city_name":"重庆市","station_name":"重庆市江津区汽车站","telephone":"023-47541928","address":"重庆市江津南门路124号"},{"city_name":"重庆市","station_name":"重庆市江津区油溪汽车站","telephone":"023-47885567","address":"重庆市江津区油溪镇"},{"city_name":"重庆市","station_name":"重庆市江津区客运中心","telephone":"023-47565129/85562604","address":"重庆市江津区鼎山大道"},{"city_name":"重庆市","station_name":"重庆市陈家坪汽车站","telephone":"023-89088988","address":"重庆市石杨路39号"},{"city_name":"重庆市","station_name":"重庆市九龙坡西彭汽车站","telephone":"023-65819056","address":"重庆市九龙坡区西彭镇西庆路55号"},{"city_name":"重庆市","station_name":"重庆市走马汽车站","telephone":"023-65770293","address":"重庆市九龙坡区走马镇津马路1号"},{"city_name":"重庆市","station_name":"重庆市合川钱塘汽车站","telephone":"暂无信息","address":"重庆市合川区"},{"city_name":"重庆市","station_name":"重庆市合川官渡汽车站","telephone":"暂无信息","address":"重庆市合川区"},{"city_name":"重庆市","station_name":"重庆市合川太和汽车站","telephone":"暂无信息","address":"重庆市太和镇接龙街"},{"city_name":"重庆市","station_name":"重庆市合川客运中心","telephone":"023-42898631","address":"重庆市合川区合阳办北环路2号"},{"city_name":"重庆市","station_name":"重庆市永川朱沱汽车站","telephone":"暂无信息","address":"重庆市永川区"},{"city_name":"重庆市","station_name":"重庆市永川汽车总站","telephone":"023-49863320","address":"重庆市永川区渝西大道中段1467号"},{"city_name":"重庆市","station_name":"重庆市巴南木洞客运站","telephone":"暂无信息","address":"重庆市巴南区"},{"city_name":"重庆市","station_name":"重庆市酉阳城北车站","telephone":"023-75559103","address":"重庆市酉阳土家族苗族自治县中多镇酉新路1号"},{"city_name":"重庆市","station_name":"重庆市酉阳汽车南站","telephone":"暂无信息","address":"重庆市酉阳土家族苗族自治县桃花园南路附近"},{"city_name":"重庆市","station_name":"重庆市渝北汽车站","telephone":"023-67821126","address":"重庆市渝北区渝长路30号"},{"city_name":"重庆市","station_name":"重庆市渝北石坪汽车站","telephone":"暂无信息","address":"重庆市渝北区石坪北路72号"},{"city_name":"重庆市","station_name":"重庆市渝北总站两路汽车站","telephone":"023-67821151","address":"重庆市渝北区五星路99号"},{"city_name":"重庆市","station_name":"重庆市渝北洛碛汽车站","telephone":"暂无信息","address":"重庆市渝北区洛张路洛碛镇"},{"city_name":"重庆市","station_name":"重庆市汽车站","telephone":"023-89033855","address":"重庆市菜袁路6号菜袁火车站旁边"},{"city_name":"重庆市","station_name":"重庆市菜园坝汽车站","telephone":"暂无信息","address":"重庆市渝中区菜袁路8号"},{"city_name":"重庆市","station_name":"重庆市朝天门长途汽车总站","telephone":"023-63736878","address":"重庆市渝中区长江滨江路8号"},{"city_name":"重庆市","station_name":"重庆市公路运输总公司长途汽车站","telephone":"023-89033877","address":"重庆市渝中区菜袁路3号"},{"city_name":"重庆市","station_name":"重庆市黔江东站","telephone":"023-79252342","address":"重庆市黔江区官坝路"},{"city_name":"重庆市","station_name":"重庆市万盛汽车站","telephone":"023-48275207","address":"重庆市万盛区塔山路附近"},{"city_name":"重庆市","station_name":"重庆市石柱黄水汽车站","telephone":"暂无信息","address":"重庆市石柱土家族自治县黄水镇"},{"city_name":"重庆市","station_name":"重庆市石柱汽车客运总站","telephone":"023-73332428","address":"重庆市石柱县南宾镇万寿大道(城南汽车站)"},{"city_name":"重庆市","station_name":"重庆市双桥区客运站","telephone":"023-48882823","address":"重庆市双桥区双北路"},{"city_name":"重庆市","station_name":"重庆市铜梁安居汽车站","telephone":"暂无信息","address":"重庆市铜梁县"},{"city_name":"重庆市","station_name":"重庆市铜梁客运中心","telephone":"023-45632724","address":"重庆市铜梁县中南路1号"},{"city_name":"重庆市","station_name":"重庆市大渡口汽车站","telephone":"023-68906054","address":"重庆市大渡口区新山村春晖路518号"},{"city_name":"重庆市","station_name":"重庆市潼南塘坝汽车站","telephone":"暂无信息","address":"重庆市潼南县"},{"city_name":"重庆市","station_name":"重庆市大足县邮亭汽车站","telephone":"023-43528744","address":"重庆市大足县邮亭镇"},{"city_name":"重庆市","station_name":"重庆市潼南江北汽车站","telephone":"暂无信息","address":"重庆市潼南县江北新城67块区"},{"city_name":"重庆市","station_name":"重庆市垫江澄溪客运站","telephone":"暂无信息","address":"重庆市垫江县"},{"city_name":"重庆市","station_name":"重庆市巫山汽车客运站","telephone":"023-57682206","address":"重庆市巫山县平湖西路491号"},{"city_name":"重庆市","station_name":"重庆市丰都车站","telephone":"023-70704792","address":"重庆市丰都县三合镇滨江西路127号"},{"city_name":"重庆市","station_name":"重庆市巫山骡坪汽车客运站","telephone":"023-57752222","address":"重庆市巫山县骡坪镇仙鹤街107号"},{"city_name":"重庆市","station_name":"重庆市奉节吐祥客运站","telephone":"暂无信息","address":"重庆市吐祥镇管家村8组向东"},{"city_name":"重庆市","station_name":"重庆市奉节港口车站","telephone":"暂无信息","address":"重庆市奉节县永安镇步云街沿江道东1-2号"},{"city_name":"重庆市","station_name":"重庆市梁平城客运站","telephone":"暂无信息","address":"重庆市梁平县"},{"city_name":"重庆市","station_name":"重庆市梁平汽车站","telephone":"023-53253633","address":"重庆市梁平县梁山镇大河路2号"},{"city_name":"重庆市","station_name":"重庆市悦达客运北站","telephone":"023-53239766","address":"重庆市梁平县机场路"},{"city_name":"重庆市","station_name":"重庆市璧山县丁家汽车站","telephone":"023-41482906","address":"重庆市璧山县丁家镇渝隆路232号"},{"city_name":"重庆市","station_name":"重庆市璧山县璧山客货运输中心","telephone":"023-41405612","address":"重庆市璧山县璧城璧永路370号"},{"city_name":"重庆市","station_name":"重庆市北碚区偏岩客运站","telephone":"暂无信息","address":"重庆市北碚区"},{"city_name":"重庆市","station_name":"重庆市北碚区水土客运汽车站","telephone":"暂无信息","address":"重庆市北碚区水土镇"},{"city_name":"重庆市","station_name":"重庆市长寿骑鞍车站","telephone":"023-40463228","address":"重庆市长寿区桃花大道18号"},{"city_name":"重庆市","station_name":"重庆市杨家坪汽车站","telephone":"023-68451288","address":"重庆市九龙坡区西郊路59号"},{"city_name":"重庆市","station_name":"重庆市九龙坡含谷客运车站","telephone":"023-65730710","address":"重庆市九龙坡区含谷镇含金路"},{"city_name":"重庆市","station_name":"重庆市合川龙市汽车站","telephone":"暂无信息","address":"重庆市合川区"},{"city_name":"重庆市","station_name":"重庆市合川双槐镇汽车站","telephone":"暂无信息","address":"重庆市合川区"},{"city_name":"重庆市","station_name":"重庆市合川汽车客运总站","telephone":"023-42748638","address":"重庆市合川市书院路187号"},{"city_name":"重庆市","station_name":"重庆市永川松溉客运站","telephone":"暂无信息","address":"重庆市永川区"},{"city_name":"重庆市","station_name":"重庆市酉阳李溪汽车站","telephone":"暂无信息","address":"重庆市李溪镇鹅池村民委员会南"},{"city_name":"重庆市","station_name":"重庆龙头寺长途汽车站","telephone":"023-89139918","address":"重庆市北部新区重庆火车北站旁"},{"city_name":"重庆市","station_name":"重庆市石柱西沱汽车客运站","telephone":"暂无信息","address":"重庆市月台南路"},{"city_name":"重庆市","station_name":"重庆市潼南汽车站","telephone":"023-44551187","address":"重庆市梓潼镇江北新城68块区"},{"city_name":"重庆市","station_name":"重庆市奉节甲高汽车客运站","telephone":"023-56685992","address":"重庆市甲高镇龙山居委会"},{"city_name":"重庆市","station_name":"重庆市涪陵区焦石汽车客运站","telephone":"暂无信息","address":"重庆市涪陵区"},{"city_name":"重庆市","station_name":"重庆市开县临江汽车客运站","telephone":"023-52812031","address":"重庆市开县临江镇福兴街"},{"city_name":"重庆市","station_name":"重庆市江津区李市汽车站","telephone":"023-47711807","address":"重庆市李市镇转盘"},{"city_name":"重庆市","station_name":"重庆市永川汽车站","telephone":"023-49851197","address":"重庆市永川区渝西大道段中段1469号"},{"city_name":"重庆市","station_name":"重庆市渝运集团渝中汽车总站","telephone":"暂无信息","address":"重庆市临江路60号-1"},{"city_name":"重庆市","station_name":"重庆市铜梁永嘉汽车站","telephone":"暂无信息","address":"重庆市铜梁县"},{"city_name":"重庆市","station_name":"重庆汽车北站","telephone":"023-86826886","address":"重庆市渝北区建新北路19号"},{"city_name":"重庆市","station_name":"沙坪坝站","telephone":"023-61656322","address":"重庆市沙坪坝区天陈路"},{"city_name":"重庆市","station_name":"四公里交通换乘枢纽","telephone":"023-88361260","address":"重庆市南坪四公里轻轨车站旁边"}]